[
 {
  "docstatus": 0,
  "doctype": "Workflow",
  "document_type": "Payment Entry",
  "is_active": 0,
  "modified": "2026-03-30 16:22:53.769018",
  "name": "Cash Payment Approval (Payment Entry)",
  "override_status": 0,
  "send_email_alert": 0,
  "states": [
   {
    "allow_edit": "CT CASH COUNTER",
    "avoid_status_override": 0,
    "doc_status": "0",
    "is_optional_state": 0,
    "message": null,
    "next_action_email_template": null,
    "parent": "Cash Payment Approval (Payment Entry)",
    "parentfield": "states",
    "parenttype": "Workflow",
    "send_email": 1,
    "state": "Draft",
    "update_field": null,
    "update_value": null,
    "workflow_builder_id": null
   },
   {
    "allow_edit": "CT CASH APPROVER",
    "avoid_status_override": 0,
    "doc_status": "0",
    "is_optional_state": 0,
    "message": null,
    "next_action_email_template": null,
    "parent": "Cash Payment Approval (Payment Entry)",
    "parentfield": "states",
    "parenttype": "Workflow",
    "send_email": 1,
    "state": "Pending Approval",
    "update_field": null,
    "update_value": null,
    "workflow_builder_id": null
   },
   {
    "allow_edit": "CT CASH COUNTER",
    "avoid_status_override": 0,
    "doc_status": "1",
    "is_optional_state": 0,
    "message": null,
    "next_action_email_template": null,
    "parent": "Cash Payment Approval (Payment Entry)",
    "parentfield": "states",
    "parenttype": "Workflow",
    "send_email": 1,
    "state": "Approved",
    "update_field": null,
    "update_value": null,
    "workflow_builder_id": null
   },
   {
    "allow_edit": "CT CASH COUNTER",
    "avoid_status_override": 0,
    "doc_status": "0",
    "is_optional_state": 0,
    "message": null,
    "next_action_email_template": null,
    "parent": "Cash Payment Approval (Payment Entry)",
    "parentfield": "states",
    "parenttype": "Workflow",
    "send_email": 1,
    "state": "Rejected",
    "update_field": null,
    "update_value": null,
    "workflow_builder_id": null
   }
  ],
  "transitions": [
   {
    "action": "Submit for Approval",
    "allow_self_approval": 0,
    "allowed": "CT CASH COUNTER",
    "condition": "doc.payment_type == \"Pay\" and doc.mode_of_payment == \"Cash\"",
    "next_state": "Pending Approval",
    "parent": "Cash Payment Approval (Payment Entry)",
    "parentfield": "transitions",
    "parenttype": "Workflow",
    "send_email_to_creator": 0,
    "state": "Draft",
    "workflow_builder_id": null
   },
   {
    "action": "Approve",
    "allow_self_approval": 0,
    "allowed": "CT CASH APPROVER",
    "condition": null,
    "next_state": "Approved",
    "parent": "Cash Payment Approval (Payment Entry)",
    "parentfield": "transitions",
    "parenttype": "Workflow",
    "send_email_to_creator": 0,
    "state": "Pending Approval",
    "workflow_builder_id": null
   },
   {
    "action": "Reject",
    "allow_self_approval": 0,
    "allowed": "CT CASH APPROVER",
    "condition": null,
    "next_state": "Rejected",
    "parent": "Cash Payment Approval (Payment Entry)",
    "parentfield": "transitions",
    "parenttype": "Workflow",
    "send_email_to_creator": 0,
    "state": "Pending Approval",
    "workflow_builder_id": null
   },
   {
    "action": "Re-submit",
    "allow_self_approval": 0,
    "allowed": "CT CASH COUNTER",
    "condition": null,
    "next_state": "Draft",
    "parent": "Cash Payment Approval (Payment Entry)",
    "parentfield": "transitions",
    "parenttype": "Workflow",
    "send_email_to_creator": 0,
    "state": "Rejected",
    "workflow_builder_id": null
   }
  ],
  "workflow_data": null,
  "workflow_name": "Cash Payment Approval (Payment Entry)",
  "workflow_state_field": "workflow_state"
 },
 {
  "docstatus": 0,
  "doctype": "Workflow",
  "document_type": "Bank Account",
  "is_active": 0,
  "modified": "2025-03-25 22:59:08.696040",
  "name": "Payment Integration Bank Account Workflow",
  "override_status": 0,
  "send_email_alert": 0,
  "states": [
   {
    "allow_edit": "All",
    "avoid_status_override": 0,
    "doc_status": "0",
    "is_optional_state": 0,
    "message": null,
    "next_action_email_template": null,
    "parent": "Payment Integration Bank Account Workflow",
    "parentfield": "states",
    "parenttype": "Workflow",
    "send_email": 1,
    "state": "Draft",
    "update_field": null,
    "update_value": null,
    "workflow_builder_id": null
   },
   {
    "allow_edit": "Bank Account User",
    "avoid_status_override": 0,
    "doc_status": "0",
    "is_optional_state": 0,
    "message": null,
    "next_action_email_template": null,
    "parent": "Payment Integration Bank Account Workflow",
    "parentfield": "states",
    "parenttype": "Workflow",
    "send_email": 1,
    "state": "Draft",
    "update_field": null,
    "update_value": null,
    "workflow_builder_id": null
   },
   {
    "allow_edit": "Bank Account Manager",
    "avoid_status_override": 0,
    "doc_status": "0",
    "is_optional_state": 0,
    "message": null,
    "next_action_email_template": null,
    "parent": "Payment Integration Bank Account Workflow",
    "parentfield": "states",
    "parenttype": "Workflow",
    "send_email": 1,
    "state": "Draft",
    "update_field": null,
    "update_value": null,
    "workflow_builder_id": null
   },
   {
    "allow_edit": "Bank Account Manager",
    "avoid_status_override": 0,
    "doc_status": "0",
    "is_optional_state": 0,
    "message": null,
    "next_action_email_template": null,
    "parent": "Payment Integration Bank Account Workflow",
    "parentfield": "states",
    "parenttype": "Workflow",
    "send_email": 1,
    "state": "Pending Approval",
    "update_field": null,
    "update_value": null,
    "workflow_builder_id": null
   },
   {
    "allow_edit": "System Manager",
    "avoid_status_override": 0,
    "doc_status": "0",
    "is_optional_state": 0,
    "message": null,
    "next_action_email_template": null,
    "parent": "Payment Integration Bank Account Workflow",
    "parentfield": "states",
    "parenttype": "Workflow",
    "send_email": 1,
    "state": "Rejected",
    "update_field": "disabled",
    "update_value": "1",
    "workflow_builder_id": null
   },
   {
    "allow_edit": "System Manager",
    "avoid_status_override": 0,
    "doc_status": "0",
    "is_optional_state": 0,
    "message": null,
    "next_action_email_template": null,
    "parent": "Payment Integration Bank Account Workflow",
    "parentfield": "states",
    "parenttype": "Workflow",
    "send_email": 1,
    "state": "Cancelled",
    "update_field": "disabled",
    "update_value": "1",
    "workflow_builder_id": null
   },
   {
    "allow_edit": "System Manager",
    "avoid_status_override": 0,
    "doc_status": "0",
    "is_optional_state": 0,
    "message": null,
    "next_action_email_template": null,
    "parent": "Payment Integration Bank Account Workflow",
    "parentfield": "states",
    "parenttype": "Workflow",
    "send_email": 1,
    "state": "Approved",
    "update_field": "disabled",
    "update_value": "0",
    "workflow_builder_id": null
   }
  ],
  "transitions": [
   {
    "action": "Request Approval",
    "allow_self_approval": 1,
    "allowed": "Bank Account User",
    "condition": null,
    "next_state": "Pending Approval",
    "parent": "Payment Integration Bank Account Workflow",
    "parentfield": "transitions",
    "parenttype": "Workflow",
    "send_email_to_creator": 0,
    "state": "Draft",
    "workflow_builder_id": null
   },
   {
    "action": "Request Approval",
    "allow_self_approval": 1,
    "allowed": "Bank Account Manager",
    "condition": null,
    "next_state": "Pending Approval",
    "parent": "Payment Integration Bank Account Workflow",
    "parentfield": "transitions",
    "parenttype": "Workflow",
    "send_email_to_creator": 0,
    "state": "Draft",
    "workflow_builder_id": null
   },
   {
    "action": "Request Approval",
    "allow_self_approval": 1,
    "allowed": "All",
    "condition": null,
    "next_state": "Pending Approval",
    "parent": "Payment Integration Bank Account Workflow",
    "parentfield": "transitions",
    "parenttype": "Workflow",
    "send_email_to_creator": 0,
    "state": "Draft",
    "workflow_builder_id": null
   },
   {
    "action": "Reject",
    "allow_self_approval": 1,
    "allowed": "Bank Account Manager",
    "condition": null,
    "next_state": "Rejected",
    "parent": "Payment Integration Bank Account Workflow",
    "parentfield": "transitions",
    "parenttype": "Workflow",
    "send_email_to_creator": 0,
    "state": "Pending Approval",
    "workflow_builder_id": null
   },
   {
    "action": "Approve",
    "allow_self_approval": 1,
    "allowed": "Bank Account Manager",
    "condition": null,
    "next_state": "Approved",
    "parent": "Payment Integration Bank Account Workflow",
    "parentfield": "transitions",
    "parenttype": "Workflow",
    "send_email_to_creator": 0,
    "state": "Pending Approval",
    "workflow_builder_id": null
   },
   {
    "action": "Cancel",
    "allow_self_approval": 1,
    "allowed": "System Manager",
    "condition": null,
    "next_state": "Cancelled",
    "parent": "Payment Integration Bank Account Workflow",
    "parentfield": "transitions",
    "parenttype": "Workflow",
    "send_email_to_creator": 0,
    "state": "Approved",
    "workflow_builder_id": null
   }
  ],
  "workflow_data": null,
  "workflow_name": "Payment Integration Bank Account Workflow",
  "workflow_state_field": "payment_integration_workflow_state"
 },
 {
  "docstatus": 0,
  "doctype": "Workflow",
  "document_type": "Payment Entry",
  "is_active": 0,
  "modified": "2025-03-25 22:59:08.977362",
  "name": "Payment Integration Payment Entry Workflow",
  "override_status": 0,
  "send_email_alert": 0,
  "states": [
   {
    "allow_edit": "All",
    "avoid_status_override": 0,
    "doc_status": "0",
    "is_optional_state": 0,
    "message": null,
    "next_action_email_template": null,
    "parent": "Payment Integration Payment Entry Workflow",
    "parentfield": "states",
    "parenttype": "Workflow",
    "send_email": 1,
    "state": "Draft",
    "update_field": null,
    "update_value": null,
    "workflow_builder_id": null
   },
   {
    "allow_edit": "Online Payments Authorizer",
    "avoid_status_override": 0,
    "doc_status": "0",
    "is_optional_state": 0,
    "message": null,
    "next_action_email_template": null,
    "parent": "Payment Integration Payment Entry Workflow",
    "parentfield": "states",
    "parenttype": "Workflow",
    "send_email": 1,
    "state": "Draft",
    "update_field": null,
    "update_value": null,
    "workflow_builder_id": null
   },
   {
    "allow_edit": "Online Payments Authorizer",
    "avoid_status_override": 0,
    "doc_status": "0",
    "is_optional_state": 0,
    "message": null,
    "next_action_email_template": null,
    "parent": "Payment Integration Payment Entry Workflow",
    "parentfield": "states",
    "parenttype": "Workflow",
    "send_email": 1,
    "state": "Pending Approval",
    "update_field": null,
    "update_value": null,
    "workflow_builder_id": null
   },
   {
    "allow_edit": "System Manager",
    "avoid_status_override": 0,
    "doc_status": "0",
    "is_optional_state": 0,
    "message": null,
    "next_action_email_template": null,
    "parent": "Payment Integration Payment Entry Workflow",
    "parentfield": "states",
    "parenttype": "Workflow",
    "send_email": 1,
    "state": "Rejected",
    "update_field": null,
    "update_value": null,
    "workflow_builder_id": null
   },
   {
    "allow_edit": "System Manager",
    "avoid_status_override": 0,
    "doc_status": "1",
    "is_optional_state": 0,
    "message": null,
    "next_action_email_template": null,
    "parent": "Payment Integration Payment Entry Workflow",
    "parentfield": "states",
    "parenttype": "Workflow",
    "send_email": 1,
    "state": "Approved",
    "update_field": null,
    "update_value": null,
    "workflow_builder_id": null
   },
   {
    "allow_edit": "System Manager",
    "avoid_status_override": 0,
    "doc_status": "2",
    "is_optional_state": 0,
    "message": null,
    "next_action_email_template": null,
    "parent": "Payment Integration Payment Entry Workflow",
    "parentfield": "states",
    "parenttype": "Workflow",
    "send_email": 1,
    "state": "Cancelled",
    "update_field": null,
    "update_value": null,
    "workflow_builder_id": null
   }
  ],
  "transitions": [
   {
    "action": "Request Approval",
    "allow_self_approval": 1,
    "allowed": "All",
    "condition": null,
    "next_state": "Pending Approval",
    "parent": "Payment Integration Payment Entry Workflow",
    "parentfield": "transitions",
    "parenttype": "Workflow",
    "send_email_to_creator": 0,
    "state": "Draft",
    "workflow_builder_id": null
   },
   {
    "action": "Request Approval",
    "allow_self_approval": 1,
    "allowed": "Online Payments Authorizer",
    "condition": null,
    "next_state": "Pending Approval",
    "parent": "Payment Integration Payment Entry Workflow",
    "parentfield": "transitions",
    "parenttype": "Workflow",
    "send_email_to_creator": 0,
    "state": "Draft",
    "workflow_builder_id": null
   },
   {
    "action": "Approve",
    "allow_self_approval": 1,
    "allowed": "Online Payments Authorizer",
    "condition": null,
    "next_state": "Approved",
    "parent": "Payment Integration Payment Entry Workflow",
    "parentfield": "transitions",
    "parenttype": "Workflow",
    "send_email_to_creator": 0,
    "state": "Pending Approval",
    "workflow_builder_id": null
   },
   {
    "action": "Reject",
    "allow_self_approval": 1,
    "allowed": "Online Payments Authorizer",
    "condition": null,
    "next_state": "Rejected",
    "parent": "Payment Integration Payment Entry Workflow",
    "parentfield": "transitions",
    "parenttype": "Workflow",
    "send_email_to_creator": 0,
    "state": "Pending Approval",
    "workflow_builder_id": null
   },
   {
    "action": "Cancel",
    "allow_self_approval": 1,
    "allowed": "System Manager",
    "condition": null,
    "next_state": "Cancelled",
    "parent": "Payment Integration Payment Entry Workflow",
    "parentfield": "transitions",
    "parenttype": "Workflow",
    "send_email_to_creator": 0,
    "state": "Approved",
    "workflow_builder_id": null
   }
  ],
  "workflow_data": null,
  "workflow_name": "Payment Integration Payment Entry Workflow",
  "workflow_state_field": "payment_integration_workflow_state"
 },
 {
  "docstatus": 0,
  "doctype": "Workflow",
  "document_type": "Bank Account",
  "is_active": 0,
  "modified": "2025-08-12 17:22:41.821450",
  "name": "Bank Account Approval",
  "override_status": 0,
  "send_email_alert": 0,
  "states": [
   {
    "allow_edit": "All",
    "avoid_status_override": 0,
    "doc_status": "0",
    "is_optional_state": 0,
    "message": null,
    "next_action_email_template": null,
    "parent": "Bank Account Approval",
    "parentfield": "states",
    "parenttype": "Workflow",
    "send_email": 1,
    "state": "Pending",
    "update_field": null,
    "update_value": "Pending",
    "workflow_builder_id": null
   },
   {
    "allow_edit": "Accounts Manager",
    "avoid_status_override": 0,
    "doc_status": "0",
    "is_optional_state": 0,
    "message": null,
    "next_action_email_template": null,
    "parent": "Bank Account Approval",
    "parentfield": "states",
    "parenttype": "Workflow",
    "send_email": 1,
    "state": "Approved",
    "update_field": null,
    "update_value": "Approved",
    "workflow_builder_id": null
   }
  ],
  "transitions": [
   {
    "action": "Approve",
    "allow_self_approval": 1,
    "allowed": "Accounts Manager",
    "condition": null,
    "next_state": "Approved",
    "parent": "Bank Account Approval",
    "parentfield": "transitions",
    "parenttype": "Workflow",
    "send_email_to_creator": 0,
    "state": "Pending",
    "workflow_builder_id": null
   },
   {
    "action": "Reject",
    "allow_self_approval": 1,
    "allowed": "Accounts Manager",
    "condition": null,
    "next_state": "Pending",
    "parent": "Bank Account Approval",
    "parentfield": "transitions",
    "parenttype": "Workflow",
    "send_email_to_creator": 0,
    "state": "Approved",
    "workflow_builder_id": null
   }
  ],
  "workflow_data": null,
  "workflow_name": "Bank Account Approval",
  "workflow_state_field": "workflow_state"
 },
 {
  "docstatus": 0,
  "doctype": "Workflow",
  "document_type": "Expense Claim",
  "is_active": 1,
  "modified": "2025-08-20 10:49:37.565862",
  "name": "Expense Claim",
  "override_status": 1,
  "send_email_alert": 0,
  "states": [
   {
    "allow_edit": "Employee Self Service",
    "avoid_status_override": 0,
    "doc_status": "0",
    "is_optional_state": 0,
    "message": null,
    "next_action_email_template": null,
    "parent": "Expense Claim",
    "parentfield": "states",
    "parenttype": "Workflow",
    "send_email": 1,
    "state": "Pending",
    "update_field": "approval_status",
    "update_value": "Draft",
    "workflow_builder_id": null
   },
   {
    "allow_edit": "Expense Approver",
    "avoid_status_override": 0,
    "doc_status": "1",
    "is_optional_state": 0,
    "message": null,
    "next_action_email_template": null,
    "parent": "Expense Claim",
    "parentfield": "states",
    "parenttype": "Workflow",
    "send_email": 1,
    "state": "Approved",
    "update_field": "approval_status",
    "update_value": "Approved",
    "workflow_builder_id": null
   },
   {
    "allow_edit": "Expense Approver",
    "avoid_status_override": 0,
    "doc_status": "0",
    "is_optional_state": 0,
    "message": null,
    "next_action_email_template": null,
    "parent": "Expense Claim",
    "parentfield": "states",
    "parenttype": "Workflow",
    "send_email": 1,
    "state": "Rejected",
    "update_field": "approval_status",
    "update_value": "Rejected",
    "workflow_builder_id": null
   }
  ],
  "transitions": [
   {
    "action": "Approve",
    "allow_self_approval": 1,
    "allowed": "Expense Approver",
    "condition": null,
    "next_state": "Approved",
    "parent": "Expense Claim",
    "parentfield": "transitions",
    "parenttype": "Workflow",
    "send_email_to_creator": 0,
    "state": "Pending",
    "workflow_builder_id": null
   },
   {
    "action": "Reject",
    "allow_self_approval": 1,
    "allowed": "Expense Approver",
    "condition": null,
    "next_state": "Rejected",
    "parent": "Expense Claim",
    "parentfield": "transitions",
    "parenttype": "Workflow",
    "send_email_to_creator": 0,
    "state": "Pending",
    "workflow_builder_id": null
   }
  ],
  "workflow_data": null,
  "workflow_name": "Expense Claim",
  "workflow_state_field": "workflow_state"
 },
 {
  "docstatus": 0,
  "doctype": "Workflow",
  "document_type": "Sales Invoice",
  "is_active": 0,
  "modified": "2025-09-16 09:57:03.982364",
  "name": "Sales Invoice",
  "override_status": 1,
  "send_email_alert": 0,
  "states": [
   {
    "allow_edit": "CT SALES ENTRY",
    "avoid_status_override": 0,
    "doc_status": "0",
    "is_optional_state": 0,
    "message": null,
    "next_action_email_template": null,
    "parent": "Sales Invoice",
    "parentfield": "states",
    "parenttype": "Workflow",
    "send_email": 1,
    "state": "Draft",
    "update_field": null,
    "update_value": null,
    "workflow_builder_id": null
   },
   {
    "allow_edit": "CT SALES ENTRY",
    "avoid_status_override": 0,
    "doc_status": "0",
    "is_optional_state": 0,
    "message": null,
    "next_action_email_template": null,
    "parent": "Sales Invoice",
    "parentfield": "states",
    "parenttype": "Workflow",
    "send_email": 1,
    "state": "Check Out",
    "update_field": null,
    "update_value": null,
    "workflow_builder_id": null
   },
   {
    "allow_edit": "CT SALES ENTRY",
    "avoid_status_override": 0,
    "doc_status": "1",
    "is_optional_state": 0,
    "message": null,
    "next_action_email_template": null,
    "parent": "Sales Invoice",
    "parentfield": "states",
    "parenttype": "Workflow",
    "send_email": 1,
    "state": "Submitted",
    "update_field": null,
    "update_value": null,
    "workflow_builder_id": null
   },
   {
    "allow_edit": "CT SALES ENTRY",
    "avoid_status_override": 0,
    "doc_status": "1",
    "is_optional_state": 0,
    "message": null,
    "next_action_email_template": null,
    "parent": "Sales Invoice",
    "parentfield": "states",
    "parenttype": "Workflow",
    "send_email": 1,
    "state": "Cancel Requested",
    "update_field": null,
    "update_value": null,
    "workflow_builder_id": null
   },
   {
    "allow_edit": "CT SALES ENTRY",
    "avoid_status_override": 0,
    "doc_status": "2",
    "is_optional_state": 0,
    "message": null,
    "next_action_email_template": null,
    "parent": "Sales Invoice",
    "parentfield": "states",
    "parenttype": "Workflow",
    "send_email": 1,
    "state": "Cancelled",
    "update_field": null,
    "update_value": null,
    "workflow_builder_id": null
   }
  ],
  "transitions": [
   {
    "action": "Check Out",
    "allow_self_approval": 1,
    "allowed": "CT SALES ENTRY",
    "condition": null,
    "next_state": "Check Out",
    "parent": "Sales Invoice",
    "parentfield": "transitions",
    "parenttype": "Workflow",
    "send_email_to_creator": 0,
    "state": "Draft",
    "workflow_builder_id": null
   },
   {
    "action": "Submit",
    "allow_self_approval": 1,
    "allowed": "CT CASH COUNTER",
    "condition": null,
    "next_state": "Submitted",
    "parent": "Sales Invoice",
    "parentfield": "transitions",
    "parenttype": "Workflow",
    "send_email_to_creator": 0,
    "state": "Check Out",
    "workflow_builder_id": null
   },
   {
    "action": "Return to Draft",
    "allow_self_approval": 1,
    "allowed": "CT CASH COUNTER",
    "condition": null,
    "next_state": "Draft",
    "parent": "Sales Invoice",
    "parentfield": "transitions",
    "parenttype": "Workflow",
    "send_email_to_creator": 0,
    "state": "Check Out",
    "workflow_builder_id": null
   },
   {
    "action": "Request Cancel",
    "allow_self_approval": 1,
    "allowed": "CT SALES ENTRY",
    "condition": null,
    "next_state": "Cancel Requested",
    "parent": "Sales Invoice",
    "parentfield": "transitions",
    "parenttype": "Workflow",
    "send_email_to_creator": 0,
    "state": "Submitted",
    "workflow_builder_id": null
   },
   {
    "action": "Approve Cancel",
    "allow_self_approval": 1,
    "allowed": "CT ADMIN",
    "condition": null,
    "next_state": "Cancelled",
    "parent": "Sales Invoice",
    "parentfield": "transitions",
    "parenttype": "Workflow",
    "send_email_to_creator": 0,
    "state": "Cancel Requested",
    "workflow_builder_id": null
   }
  ],
  "workflow_data": null,
  "workflow_name": "Sales Invoice",
  "workflow_state_field": "workflow_state"
 },
 {
  "docstatus": 0,
  "doctype": "Workflow",
  "document_type": "Daliy Cash Entry",
  "is_active": 1,
  "modified": "2026-01-27 14:10:38.140008",
  "name": "Daliy Cash",
  "override_status": 0,
  "send_email_alert": 0,
  "states": [
   {
    "allow_edit": "CT CASH APPROVER",
    "avoid_status_override": 0,
    "doc_status": "0",
    "is_optional_state": 0,
    "message": null,
    "next_action_email_template": null,
    "parent": "Daliy Cash",
    "parentfield": "states",
    "parenttype": "Workflow",
    "send_email": 1,
    "state": "Pending",
    "update_field": null,
    "update_value": null,
    "workflow_builder_id": null
   },
   {
    "allow_edit": "CT CASH APPROVER UNDER 5000",
    "avoid_status_override": 0,
    "doc_status": "1",
    "is_optional_state": 0,
    "message": null,
    "next_action_email_template": null,
    "parent": "Daliy Cash",
    "parentfield": "states",
    "parenttype": "Workflow",
    "send_email": 1,
    "state": "Approved",
    "update_field": null,
    "update_value": null,
    "workflow_builder_id": null
   },
   {
    "allow_edit": "CT CASH APPROVER",
    "avoid_status_override": 0,
    "doc_status": "1",
    "is_optional_state": 0,
    "message": null,
    "next_action_email_template": null,
    "parent": "Daliy Cash",
    "parentfield": "states",
    "parenttype": "Workflow",
    "send_email": 1,
    "state": "Approved",
    "update_field": null,
    "update_value": null,
    "workflow_builder_id": null
   }
  ],
  "transitions": [
   {
    "action": "Approve",
    "allow_self_approval": 1,
    "allowed": "CT CASH APPROVER",
    "condition": null,
    "next_state": "Approved",
    "parent": "Daliy Cash",
    "parentfield": "transitions",
    "parenttype": "Workflow",
    "send_email_to_creator": 0,
    "state": "Pending",
    "workflow_builder_id": null
   },
   {
    "action": "Approve",
    "allow_self_approval": 1,
    "allowed": "CT CASH APPROVER UNDER 5000",
    "condition": "doc.amount>5000",
    "next_state": "Approved",
    "parent": "Daliy Cash",
    "parentfield": "transitions",
    "parenttype": "Workflow",
    "send_email_to_creator": 0,
    "state": "Pending",
    "workflow_builder_id": null
   }
  ],
  "workflow_data": null,
  "workflow_name": "Daliy Cash",
  "workflow_state_field": "workflow_state"
 }
]